[{
      "id":"2",
      "type":"Квартира",
      "page":"",
      "rent":"",
      "rooms":"1",
      "surface":"41",
      "surface_land":"",
      "price":"$50000",
      "price_sqmt":"",
      "floor":"5",
      "floors":"5",
      "parking":"Прибудинкова територія під охороною",
      "region":"",
      "location":"м. Запоріжжя",
      "address":"вул. Барвиста, 1",
      "object":"Місто Мрія",
      "coordinates":"",
      "date":"2020-08-15",
      "seller":"Агенція Продавець",
      "phone":"000000000000","description":"",
      "link":"","images":""},{
      "id":"1",
      "type":"Квартира",
      "page":"",
      "rent":"",
      "rooms":"4",
      "surface":"100",
      "surface_land":"",
      "price":"$100000",
      "price_sqmt":"",
      "floor":"1",
      "floors":"2",
      "parking":"Прибудинкова територія",
      "region":"",
      "location":"м. Запоріжжя",
      "address":"вул. Прохідна, 200",
      "object":"",
      "coordinates":"",
      "date":"2020-08-14",
      "seller":"Агенція Продавець",
      "phone":"000000000000","description":"",
      "link":"","images":""},{
      "id":"0",
      "type":"Квартира",
      "page":"",
      "rent":"",
      "rooms":"2",
      "surface":"59",
      "surface_land":"",
      "price":"$80000",
      "price_sqmt":"",
      "floor":"2",
      "floors":"6",
      "parking":"Прибудинкова огороджена територія",
      "region":"",
      "location":"м. Запоріжжя",
      "address":"вул. Північна, 22",
      "object":"",
      "coordinates":"",
      "date":"2020-08-13",
      "seller":"Агенція Продавець",
      "phone":"000000000000","description":"",
      "link":"","images":""}]
